lll_simple_ai_shared/__init__.py
lll_simple_ai_shared/data_models/__init__.py
lll_simple_ai_shared/data_models/behavior_models.py
lll_simple_ai_shared/data_models/episodic_memories_models.py
lll_simple_ai_shared/data_models/recall_results_models.py
lll_simple_ai_shared/data_models/understand_models.py
lll_simple_ai_shared/utils/__init__.py
lll_simple_ai_shared/utils/extract.py
lll_simple_ai_shared/utils/prompt_template.py
lll_simple_ai_shared-0.1.8.dist-info/licenses/LICENSE
lll_simple_ai_shared-0.1.8.dist-info/METADATA
lll_simple_ai_shared-0.1.8.dist-info/WHEEL
lll_simple_ai_shared-0.1.8.dist-info/top_level.txt
lll_simple_ai_shared-0.1.8.dist-info/RECORD
