Metadata-Version: 2.4
Name: lll-simple-ai-shared
Version: 0.1.8
Summary: 数据类型定义
Requires-Python: >=3.8
License-File: LICENSE
Dynamic: license-file
